AUTHORS.rst
CONTRIBUTING.rst
HISTORY.rst
LICENSE
MANIFEST.in
README.rst
setup.cfg
setup.py
demo_site/__init__.py
demo_site/admin.py
demo_site/apps.py
demo_site/models.py
demo_site/urls.py
demo_site/views.py
demo_site/migrations/0001_initial.py
demo_site/migrations/0002_auto_20181003_1634.py
demo_site/migrations/0003_auto_20181003_1822.py
demo_site/migrations/__init__.py
demo_site/static/css/demo_site.css
demo_site/static/js/demo_site.js
demo_site/templates/demo_site/index.html
django_demo_site.egg-info/PKG-INFO
django_demo_site.egg-info/SOURCES.txt
django_demo_site.egg-info/dependency_links.txt
django_demo_site.egg-info/not-zip-safe
django_demo_site.egg-info/requires.txt
django_demo_site.egg-info/top_level.txt