Metadata-Version: 1.1
Name: django-demo-site
Version: 0.1.0
Summary: A reusable app to help manage a demo site.
Home-page: https://github.com/weholt/django-demo-site
Author: Thomas Weholt
Author-email: thomas@weholt.org
License: MIT
Keywords: django-demo-site
Platform: UNKNOWN
Classifier: Development Status :: 3 - Alpha
Classifier: Framework :: Django :: 2.0
Classifier: Intended Audience :: Developers
Classifier: License :: OSI Approved :: BSD License
Classifier: Natural Language :: English
Classifier: Programming Language :: Python :: 2
Classifier: Programming Language :: Python :: 2.7
Classifier: Programming Language :: Python :: 3
Classifier: Programming Language :: Python :: 3.4
Classifier: Programming Language :: Python :: 3.5
Classifier: Programming Language :: Python :: 3.6
